python_dev_tools/__init__.py
python_dev_tools/whataformatter.py
python_dev_tools/whatalinter.py
python_dev_tools-2022.5.26.dist-info/entry_points.txt
python_dev_tools-2022.5.26.dist-info/LICENSE
python_dev_tools-2022.5.26.dist-info/WHEEL
python_dev_tools-2022.5.26.dist-info/METADATA
python_dev_tools-2022.5.26.dist-info/RECORD
