Metadata-Version: 2.1
Name: python-dev-tools
Version: 2022.5.26
Summary: Needed and up-to-date tools to develop in Python
Home-page: https://github.com/vpoulailleau/python-dev-tools
License: BSD-3-Clause
Keywords: python_dev_tools,development,tools
Author: Vincent Poulailleau
Author-email: vpoulailleau@gmail.com
Requires-Python: >=3.7,<4.0
Classifier: Development Status :: 4 - Beta
Classifier: Intended Audience :: Developers
Classifier: License :: OSI Approved :: BSD License
Classifier: Natural Language :: English
Classifier: Programming Language :: Python :: 3
Classifier: Programming Language :: Python :: 3.10
Classifier: Programming Language :: Python :: 3.7
Classifier: Programming Language :: Python :: 3.8
Classifier: Programming Language :: Python :: 3.9
Classifier: Topic :: Utilities
Requires-Dist: Sphinx (>=4,<5)
Requires-Dist: autoflake (>=1,<2)
Requires-Dist: black (>=22,<23)
Requires-Dist: coverage[toml] (>=6,<7)
Requires-Dist: darglint (>=1,<2)
Requires-Dist: dlint (>=0,<1)
Requires-Dist: doc8 (>=0,<1)
Requires-Dist: docformatter (>=1,<2)
Requires-Dist: flake8 (>=4,<5)
Requires-Dist: flake8-2020 (>=1,<2)
Requires-Dist: flake8-annotations (>=2,<3)
Requires-Dist: flake8-annotations-complexity (>=0,<1)
Requires-Dist: flake8-annotations-coverage (>=0,<1)
Requires-Dist: flake8-bandit (>=3,<4)
Requires-Dist: flake8-black (>=0,<1)
Requires-Dist: flake8-broken-line (>=0,<1)
Requires-Dist: flake8-bugbear (>=22,<23)
Requires-Dist: flake8-builtins (>=1,<2)
Requires-Dist: flake8-comprehensions (>=3,<4)
Requires-Dist: flake8-debugger (>=4,<5)
Requires-Dist: flake8-docstrings (>=1,<2)
Requires-Dist: flake8-eradicate (>=1,<2)
Requires-Dist: flake8-expression-complexity (>=0,<1)
Requires-Dist: flake8-fixme (>=1,<2)
Requires-Dist: flake8-functions (>=0,<1)
Requires-Dist: flake8-isort (>=4,<5)
Requires-Dist: flake8-logging-format (>=0,<1)
Requires-Dist: flake8-mutable (>=1,<2)
Requires-Dist: flake8-pytest-style (>=1,<2)
Requires-Dist: flake8-quotes (>=3,<4)
Requires-Dist: flake8-rst-docstrings (>=0,<1)
Requires-Dist: flake8-simplify (>=0,<1)
Requires-Dist: flake8-string-format (>=0,<1)
Requires-Dist: flake8-tidy-imports (>=4,<5)
Requires-Dist: flake8-typing-imports (>=1,<2)
Requires-Dist: flake8-use-fstring (>=1,<2)
Requires-Dist: flake8-variables-names (>=0,<1)
Requires-Dist: pep8-naming (>=0,<1)
Requires-Dist: pip (>=22,<23)
Requires-Dist: pybetter (>=0,<1)
Requires-Dist: pycln (>=1,<2)
Requires-Dist: pycodestyle (>=2,<3)
Requires-Dist: pydocstyle (>=6,<7)
Requires-Dist: pyflakes (>=2,<3)
Requires-Dist: pytest (>=7,<8)
Requires-Dist: pytest-cov (>=3,<4)
Requires-Dist: pytest-sugar (>=0,<1)
Requires-Dist: pyupgrade (>=2,<3)
Requires-Dist: removestar (>=1,<2)
Requires-Dist: ssort (>=0,<1)
Requires-Dist: tox (>=3,<4)
Requires-Dist: tox-travis (>=0,<1)
Requires-Dist: wemake-python-styleguide (>=0.16,<0.17)
Project-URL: Documentation, https://python-dev-tools.readthedocs.io/en/latest/
Project-URL: Repository, https://github.com/vpoulailleau/python-dev-tools
